Assignment_1/modules/half_adder_dataflow.v
// This code describes a dataflow model of a half adder logic circuit
module half_adder(a, b, s, c);
input a;
input b;
output s;
output c;
assign s = a ^ b;
assign c = a & b;
endmodule

Assignment_1/full_adder.v
module full_adder(a, b, cin, s, cout);

input a, b, cin;
wire c0, s0, c1;
output cout,s;

half_adder ha1(a, b, s0, c0);
half_adder ha2(s0, cin, s, c1);
or(cout, c0, c1);

endmodule

Assignment_1/tb_full_adder.v
// This coutode descoutribes a testbencouth for testing and simulating the full adder coutircoutuit model
`timescale 1ns/1ps
module tb_full_adder;
reg a, b, cin;
wire s, cout;
full_adder f1(a, b, cin, s, cout);

initial 
begin
    $dumpfile("test_full_adder.vcd");
    $dumpvars(1, tb_full_adder);
    a = 1'b0;
    b = 1'b0;
    cin = 1'b0;
    #20
    a = 1'b0;
    b = 1'b0;
    cin = 1'b1;
    #20
    a = 1'b0;
    b = 1'b1;
    cin = 1'b0;
    #20
    a = 1'b0;
    b = 1'b1;
    cin = 1'b1;
    #20
    a = 1'b1;
    b = 1'b0;
    cin = 1'b0;
    #20
    a = 1'b1;
    b = 1'b0;
    cin = 1'b1;
    #20
    a = 1'b1;
    b = 1'b1;
    cin = 1'b0;
    #20
    a = 1'b1;
    b = 1'b1;
    cin = 1'b1;
    # 30 $finish;
end
initial $monitor($time, " a = %b, b = %b, cin = %b, cout = %b, s = %b ", a, b, cin, cout, s);
endmodule

Assignment_1/test_full_adder.vcd
$date
	Wed Aug 14 09:11:51 2024
$end
$version
	Icarus Verilog
$end
$timescale
	1ps
$end
$scope module tb_full_adder $end
$var wire 1 ! s $end
$var wire 1 " cout $end
$var reg 1 # a $end
$var reg 1 $ b $end
$var reg 1 % cin $end
$upscope $end
$enddefinitions $end
#0
$dumpvars
0%
0$
0#
0"
0!
$end
#20000
1!
1%
#40000
0%
1$
#60000
1"
0!
1%
#80000
0"
1!
0%
0$
1#
#100000
1"
0!
1%
#120000
0%
1$
#140000
1!
1%
