Assignment_2/dflipflop_withreset.v
// This code demonstrates a behavioural model for the D-flip flop circuit with the option of resettt
module dflipflop_withreset(q, qbar, d, rst, clk);
output q, qbar;
input d, rst, clk;
reg q, qbar;
always@(posedge clk)
    begin 
        if (~rst)
            begin
            q = 1'b0;
            qbar = 1'b1;
            end
        else
            begin
            q = d;
            qbar = ~d;
            end
    end
endmodule

Assignment_2/tb_dflipflop_withreset.v
// This code describes a testbench for testing the d flip flop with reset module
`timescale 1ns/1ps
module tb_dflipflop_withreset();
reg d, rst, clk;
wire q, qbar;
dflipflop_withreset dff(q, qbar, d, rst, clk);
initial 
begin
    clk = 1'b0;
    forever #10 clk = ~clk;
end
initial
begin
    rst = 1'b0;
    #15
    rst = 1'b1;
    d = 1'b0;
    #10
    d = 1'b1;
    #20
    rst = 1'b0;
    #10
    rst = 1'b1;
    #20
    d = 1'b0;
    #20
    d = 1'b1;
    #30 $finish;
end
initial $monitor($time, " clk = %b, rst = %b, d = %b, q = %b, qbar = %b ", clk, rst, d, q, qbar);
endmodule
// The initial value of q and qbar will be denoted by'x' because it is undefined until the first positive edge of clock

Assignment_2/simulation/waveforms/test_dflipflop.vcd
$date
	Thu Aug 15 23:46:14 2024
$end
$version
	Icarus Verilog
$end
$timescale
	1ps
$end
$scope module tb_dflipflop_withreset $end
$var wire 1 ! qbar $end
$var wire 1 " q $end
$var reg 1 # clk $end
$var reg 1 $ d $end
$var reg 1 % rst $end
$scope module dff $end
$var wire 1 # clk $end
$var wire 1 $ d $end
$var wire 1 % rst $end
$var reg 1 " q $end
$var reg 1 ! qbar $end
$upscope $end
$upscope $end
$enddefinitions $end
#0
$dumpvars
0%
x$
0#
0"
1!
$end
#10000
1#
#15000
0$
1%
#20000
0#
#25000
1$
#30000
0!
1"
1#
#40000
0#
#45000
1!
0"
0%
#50000
1#
#55000
1%
#60000
0#
#70000
0!
1"
1#
#75000
0$
#80000
0#
#90000
1!
0"
1#
#95000
1$
#100000
0#
#110000
0!
1"
1#
