Assignment_2/decoder.v
// This code demonstrates the decoder module to display 3-bit Johnson counter results on the Seven-Segment display
module decoder(cntr, Sevem_Seg);
input [2:0] cntr;
output [7:0] Seven_Seg;
reg [6:0] val;
assign Seven_Seg = {1'b1, ~val} // Concatenate bits for decimal and counter value (value negated because Seven Segment display is active low)
always@(cntr) // Whenever counter value changes -> get value for display
begin
    case(cntr)
    3'd0: val = 7'b0111111;
    3'd1: val = 7'b0000011;
    3'd2: val = 7'b1011011;
    3'd3: val = 7'b1001111;
    3'd4: val = 7'b1100110;
    3'd5: val = 7'b1111101;
    3'd6: val = 7'b1111101;
    3'd7: val = 7'b0000111;
	3'd8: val = 7'b1111111;
    3'd9: val = 7'b1101111;
    endcase
end
endmodule

Assignment_2/dflipflop_withreset.v
// This code demonstrates a behavioural model for the D-flip flop circuit with the option of resettt
module dflipflop_withreset(q, qbar, d, rst, clk);
output q, qbar;
input d, rst, clk;
reg q, qbar;
always@(posedge clk)
    begin 
        if (~rst)
            begin
            q = 1'b0;
            qbar = 1'b1;
            end
        else
            begin
            q = d;
            qbar = ~d;
            end
    end
endmodule

Assignment_2/clk_divider.v
// This code demonstrates a clock divider module to reduce clock frequency to observe results in an FPGA board
module clk_divider(outClk, inClk, reset);
input inClk;
input reset;
output reg outClk;
//reg clockCount;
reg [25:0] clockCount;

always@(negedge reset or posedge inClk)
begin
    if (reset == 1'b0)
        begin
            outClk = 1'b0;
            //clockCount = 1'd0;
            clockCount = 26'd0;
        end
    else
        begin
        // if (clockCount >= 1'd1)
        if (clockCount >= 26'd50000000)
            begin
                // clockCount = 1'd0;
                clockCount = 26'd0;
                outClk = ~ outClk;
            end
        clockCount <= clockCount + 1;

        end
end
endmodule

Assignment_2/johnson_counter.v
// This code demonstrates a trhee-bit Johnson Counter circuit model
module three_bit_johnson_counter(Seven_Seg, in_clk, rst, digit, out_clk);
input in_clk, rst;
output out_clk;
output [7:0] Seven_Seg;
output [3:0] digit;
output [2:0] cntr;

wire q0, q1, q2;
wire q2bar, q1bar, q0bar;

assign digit = 4'b0001; //this enables seven seg display.
assign cntr = {q2,q1,q0};
clk_divider cd0(in_clk, rst, out_clk);
dflipflop_withreset d2(q2, q2bar, q1, rst, out_clk);
dflipflop_withreset d1(q1, q1bar, q0, rst, out_clk);
dflipflop_withreset d0(q0, q0bar, q2bar, rst, out_clk);
decoder dc0(cntr, Seven_Seg);

endmodule

Assignment_2/testbenches/tb_johnson_counter.v
// This code serves as a testbench to simulate the Johnson counter
`timescale 1ns/1ps
module tb_three_bit_johnson_counter();
reg in_clk, rst;
wire out_clk;
wire [2:0] cntr;
wire [7:0] Seven_Seg;
wire [3:0] digit;
three_bit_johnson_counter jc(Seven_Seg, digit, in_clk, rst);
initial 
begin
    in_clk = 1'b0;
    forever #10 in_clk = ~in_clk;
end
initial
begin
    $dumpfile("test_johnson_counter.vcd");
    $dumpvars(0, tb_three_bit_johnson_counter);
    rst = 1'b0;
    #5
    rst = 1'b1;
    #200 $finish;
end
initial $monitor($time, " in_clk = %b, rst = %b, digit = %b, Seven_Seg = %b", in_clk, rst, digit, Seven_Seg);
endmodule

Assignment_2/test_johnson_counter.vcd
$date
	Mon Aug 19 11:53:58 2024
$end
$version
	Icarus Verilog
$end
$timescale
	1ps
$end
$scope module tb_three_bit_johnson_counter $end
$var wire 4 ! digit [3:0] $end
$var wire 8 " Seven_Seg [7:0] $end
$var reg 1 # in_clk $end
$var reg 1 $ rst $end
$scope module jc $end
$var wire 4 % digit [3:0] $end
$var wire 1 # in_clk $end
$var wire 1 $ rst $end
$var wire 1 & q2bar $end
$var wire 1 ' q2 $end
$var wire 1 ( q1bar $end
$var wire 1 ) q1 $end
$var wire 1 * q0bar $end
$var wire 1 + q0 $end
$var wire 1 , out_clk $end
$var wire 3 - cntr [2:0] $end
$var wire 8 . Seven_Seg [7:0] $end
$scope module cd0 $end
$var wire 1 # inClk $end
$var wire 1 $ reset $end
$var reg 26 / clockCount [25:0] $end
$var reg 1 , outClk $end
$upscope $end
$scope module d0 $end
$var wire 1 , clk $end
$var wire 1 $ rst $end
$var wire 1 & d $end
$var reg 1 + q $end
$var reg 1 * qbar $end
$upscope $end
$scope module d1 $end
$var wire 1 , clk $end
$var wire 1 + d $end
$var wire 1 $ rst $end
$var reg 1 ) q $end
$var reg 1 ( qbar $end
$upscope $end
$scope module d2 $end
$var wire 1 , clk $end
$var wire 1 ) d $end
$var wire 1 $ rst $end
$var reg 1 ' q $end
$var reg 1 & qbar $end
$upscope $end
$scope module dc0 $end
$var wire 3 0 cntr [2:0] $end
$var wire 8 1 Seven_Seg [7:0] $end
$var reg 7 2 val [6:0] $end
$upscope $end
$upscope $end
$upscope $end
$enddefinitions $end
#0
$dumpvars
b111111 2
b11000000 1
b0 0
b0 /
b11000000 .
b0 -
0,
0+
1*
0)
1(
0'
1&
b1 %
0$
0#
b11000000 "
b1 !
$end
#5000
1$
#10000
b1 /
1#
#20000
0#
#30000
b10 /
1#
#40000
0#
#50000
b11 /
1#
#60000
0#
#70000
b100 /
1#
#80000
0#
#90000
b101 /
1#
#100000
0#
#110000
b110 /
1#
#120000
0#
#130000
b111 /
1#
#140000
0#
#150000
b1000 /
1#
#160000
0#
#170000
b1001 /
1#
#180000
0#
#190000
b1010 /
1#
